pinion/__init__.py
pinion/_version.py
pinion/common.py
pinion/generate.py
pinion/get.py
pinion/serve.py
pinion/template.py
pinion/ui.py
pinion/resources/indexTemplate.html
pinion/resources/pinion.css
pinion/resources/pinion.js
Pinion-0.3.0.dist-info/LICENSE
Pinion-0.3.0.dist-info/METADATA
Pinion-0.3.0.dist-info/WHEEL
Pinion-0.3.0.dist-info/entry_points.txt
Pinion-0.3.0.dist-info/top_level.txt
Pinion-0.3.0.dist-info/RECORD
