Metadata-Version: 2.1
Name: Pinion
Version: 0.3.0
Summary: Create interactive pinout diagrams for KiCAD PCBs
Home-page: https://github.com/yaqwsx/Pinion
Author: Jan Mrázek
Author-email: email@honzamrazek.cz
License: UNKNOWN
Platform: UNKNOWN
Classifier: Programming Language :: Python :: 3
Classifier: License :: OSI Approved :: MIT License
Classifier: Operating System :: OS Independent
Requires-Python: >=3.7
License-File: LICENSE
Requires-Dist: click (>=7.1)
Requires-Dist: ruamel.yaml
Requires-Dist: pcbdraw (>=1.0)
Requires-Dist: pcbnewTransition (<=0.4,>=0.2)
